Metadata-Version: 2.4
Name: crunch-cli
Version: 10.9.0
Summary: crunch-cli - CLI of the CrunchDAO Platform
Home-page: https://github.com/crunchdao/crunch-cli
Author: Enzo CACERES
Author-email: enzo.caceres@crunchdao.com
Keywords: package development template
Classifier: Intended Audience :: Developers
Classifier: Programming Language :: Python :: 3.7
Requires-Python: >=3
Requires-Dist: click
Requires-Dist: crunch-convert>=0.4.1
Requires-Dist: crunch-encrypt
Requires-Dist: coloredlogs
Requires-Dist: dataclasses_json
Requires-Dist: inquirer
Requires-Dist: joblib
Requires-Dist: libcst
Requires-Dist: pandas
Requires-Dist: psutil
Requires-Dist: pyarrow
Requires-Dist: python-dotenv
Requires-Dist: requests
Requires-Dist: requests-toolbelt
Requires-Dist: requirements-parser>=0.11.0
Requires-Dist: scikit-learn
Requires-Dist: tqdm
Provides-Extra: test
Requires-Dist: parameterized; extra == "test"
Requires-Dist: pytest; extra == "test"
Provides-Extra: dev
Requires-Dist: flask; extra == "dev"
Dynamic: author
Dynamic: author-email
Dynamic: classifier
Dynamic: description
Dynamic: description-content-type
Dynamic: home-page
Dynamic: keywords
Dynamic: provides-extra
Dynamic: requires-dist
Dynamic: requires-python
Dynamic: summary
